ALU_control.v
module ALU_control (
	input [1:0] ALUOp_i,
	input [2:0] Funct3_i,
	input [6:0] Funct7_i,
	
	output reg [3:0] ALUCtrl_o
);

	always @(*) begin
		case (AlUOp_i)
			2'b00: begin
				ALUCtrl_o = ((Funct3_i==3'b000)&&(Funct7_i==7'b0000000)) ? 4'b0000 :
					    ((Funct3_i==3'b000)&&(Funct7_i==7'b0100000)) ? 4'b0000 :
			end
		endcase
	end

endmodule

ALU.v
module ALU (
	input [31:0] OperandA_i,
	input [31:0] OperandB_i,

	input [3:0] ALUCtrl_i,
	input [2:0] Flagsel_i,	// Comes from Funct3 

	output reg [31:0] Result_o,
	output reg Flag_o	
);

	parameter EQ_case	= 000,
		  NE_case	= 001,
	  	  LT_case	= 100,
		  GE_case	= 101,
		  LTU_case	= 110,
		  GEU_case	= 111;	  

	reg EQ, NE, LT, GE, LTU, GEU;

	always @(*) begin
		case (ALUCtrl_i)
			4'b0000: Result_o = OperandA_i	+	OperandB_i;
			4'b0001: begin
		       		Result_o = OperandA_i	-	OperandB_i;
				EQ       = (OperandA_i == OperandB_i) ? 1'b1 : 1'b0;
				NE	 = (OperandA_i == OperandB_i) ? 1'b0 : 1'b1;
				LT	 = ($signed(OperandA_i) < $signed(OperandB_i)) ? 1'b1 : 1'b0;
				GE	 = ($signed(OperandA_i) >= $signed(OperandB_i)) ? 1'b1 : 1'b0;
				LTU	 = (OperandA_i < OperandB_i) ? 1'b1 : 1'b0;
				GEU	 = (OperandA_i >= OperandB_i) ? 1'b1 : 1'b0;
			end
			4'b0010: Result_o = OperandA_i	<<	OperandB_i;
		       	4'b0011: Result_o = OperandA_i	^	OperandB_i;
			4'b0100: Result_o = OperandA_i	>>	OperandB_i;
			4'b0101: Result_o = OperandA_i	>>>	OperandB_i;
			4'b0110: Result_o = OperandA_i	|	OperandB_i;
			4'b0111: Result_o = OperandA_i	&	OperandB_i;
			4'b1000: Result_o = OperandB_i	<<	12;
			default: Result_o = 32'h00000000;	
		endcase
		
	end

	always @(*) begin 
		case (Flagsel_i)
			EQ_case	: Flag_o = EQ;
			NE_case	: Flag_o = NE;
			LT_case	: Flag_o = LT;
			GE_case	: Flag_o = GE;
			LTU_case: Flag_o = LTU;
			GEU_case: Flag_o = GEU;
			default : Flag_o = 1'b0;			
		endcase
	end

endmodule

ALU_and_ALU_control.v
`include "ALU.v"
`include "ALU_control.v"



module ALU_and_ALU_control (
	input [31:0] OperandA_i,
    input [31:0] OperandB_i,
	input [6:0] Funct7_i,
	input [2:0] Funct3_i,
	input [1:0] ALUOp_i,

	output [31:0] Result_o,
	output Flag_o
);


 
          wire [3:0] ALUCtrl_wire;
  
          ALU ALU_dut (
                  .OperandA_i (OperandA_i),
                  .OperandB_i (OperandB_i),
                  .ALUCtrl_i (ALUCtrl_wire),
                  .Flagsel_i (Funct3_i),
  
                  .Result_o (Result_o),
                  .Flag_o (Flag_o)
          );
  
          ALU_control ALU_control_dut (
                  .ALUOp_i (ALUOp_i),
                  .Funct3_i (Funct3_i),
                  .Funct7_i (Funct7_i),
 
                  .ALUCtrl_o (ALUCtrl_wire)
          );



endmodule

ALU_and_ALU_control_tb.v
`timescale 1ns/1ns
`include "ALU_and_ALU_control.v"


module ALU_and_ALU_control_tb;

	reg [2:0] Funct3_i; // For ALU and ALU_control
	reg [6:0] Funct7_i; // For ALU_control

	reg [31:0] OperandA_i, OperandB_i; // For ALU
        reg [1:0] ALUOp_i; // For ALU_control

	wire [31:0] Result_o;
	wire Flag_o;	

	ALU_and_ALU_control dut (
		.Funct3_i (Funct3_i),
		.Funct7_i (Funct7_i),
		.ALUOp_i (ALUOp_i),
		.OperandA_i (OperandA_i),
		.OperandB_i (OperandB_i),
		.Result_o (Result_o),
		.Flag_o (Flag_o)
	);

	initial begin 
		
		$dumpfile("ALU_and_ALU_control_tb.vcd");
		$dumpvars(0, ALU_and_ALU_control_tb);


		$display("Arithmetic-Logic Operations:");
		OperandA_i=20; OperandB_i=30; Funct3_i=3'b000; Funct7_i=7'b0000000; ALUOp_i=2'b00; // Add
		#20;
		display;

		OperandA_i=20; OperandB_i=-30; Funct3_i=3'b000; Funct7_i=7'b0100000; ALUOp_i=2'b00; // Sub
		#20;
		display;

		OperandA_i=5; OperandB_i=2; Funct3_i=3'b001; Funct7_i=7'b0000000; ALUOp_i=2'b00;   // Sll 
		#20;
		display;

		OperandA_i=3; OperandB_i=5; Funct3_i=3'b100; Funct7_i=7'b0000000; ALUOp_i=2'b00;   // Xor 
		#20;
		display;

		OperandA_i=20; OperandB_i=2; Funct3_i=3'b101; Funct7_i=7'b0000000; ALUOp_i=2'b00;  // Srl
		#20;
		display;

		OperandA_i=-20; OperandB_i=2; Funct3_i=3'b101; Funct7_i=7'b0100000; ALUOp_i=2'b00; // Sra
		#20;
		display;

		OperandA_i=8; OperandB_i=5; Funct3_i=3'b110; Funct7_i=7'b0000000; ALUOp_i=2'b00;   // Or
		#20;
		display;

		OperandA_i=8; OperandB_i=5; Funct3_i=3'b111; Funct7_i=7'b0000000; ALUOp_i=2'b00;   // And 
		#20;
		display;

		// Load-Store
		$display("");
		$display("Load-Store:");
		OperandA_i=20; OperandB_i=30; Funct3_i=3'b000; Funct7_i=7'b0000000; ALUOp_i=2'b01; // Load-Store
		#20;
		display;

		// Conditional Branch
		$display("");
		$display("Conditional Branch:");
		OperandA_i=20; OperandB_i=20; Funct3_i=3'b000; Funct7_i=7'b0000000; ALUOp_i=2'b10; // BEQ (Condition true case)
		#20;
		display;

		OperandA_i=30; OperandB_i=20; Funct3_i=3'b000; Funct7_i=7'b0000000; ALUOp_i=2'b10; // BEQ (Condition false case) 
		#20;
		display;

		// LUI
		$display("");
		$display("Load upper immediate:");
		OperandA_i=30; OperandB_i=5; Funct3_i=3'b100; Funct7_i=7'b0000000; ALUOp_i=2'b11;   // LUI 
		#20;
		display;


	end

		task display;
			$display("OperandA= %d, OperandB= %d, Funct3= %b, Funct7= %b, ALUOp= %b, Result= %d, Flag= %b",
			$signed(OperandA_i),$signed(OperandB_i), Funct3_i, Funct7_i, ALUOp_i, $signed(Result_o), Flag_o);
		endtask	

endmodule

ALU_and_ALU_control_tb.vcd
$date
	Wed Apr 10 21:40:12 2024
$end
$version
	Icarus Verilog
$end
$timescale
	1ns
$end
$scope module ALU_and_ALU_control_tb $end
$var wire 32 ! Result_o [31:0] $end
$var wire 1 " Flag_o $end
$var reg 2 # ALUOp_i [1:0] $end
$var reg 3 $ Funct3_i [2:0] $end
$var reg 7 % Funct7_i [6:0] $end
$var reg 32 & OperandA_i [31:0] $end
$var reg 32 ' OperandB_i [31:0] $end
$scope module dut $end
$var wire 2 ( ALUOp_i [1:0] $end
$var wire 3 ) Funct3_i [2:0] $end
$var wire 7 * Funct7_i [6:0] $end
$var wire 32 + OperandA_i [31:0] $end
$var wire 32 , OperandB_i [31:0] $end
$var wire 32 - Result_o [31:0] $end
$var wire 1 " Flag_o $end
$var wire 4 . ALUCtrl_wire [3:0] $end
$scope module ALU_control_dut $end
$var wire 2 / ALUOp_i [1:0] $end
$var wire 3 0 Funct3_i [2:0] $end
$var wire 7 1 Funct7_i [6:0] $end
$var reg 4 2 ALUCtrl_o [3:0] $end
$upscope $end
$scope module ALU_dut $end
$var wire 4 3 ALUCtrl_i [3:0] $end
$var wire 3 4 Flagsel_i [2:0] $end
$var wire 32 5 OperandA_i [31:0] $end
$var wire 32 6 OperandB_i [31:0] $end
$var parameter 32 7 EQ_case $end
$var parameter 32 8 GEU_case $end
$var parameter 32 9 GE_case $end
$var parameter 32 : LTU_case $end
$var parameter 32 ; LT_case $end
$var parameter 32 < NE_case $end
$var reg 1 = EQ $end
$var reg 1 " Flag_o $end
$var reg 1 > GE $end
$var reg 1 ? GEU $end
$var reg 1 @ LT $end
$var reg 1 A LTU $end
$var reg 1 B NE $end
$var reg 32 C Result_o [31:0] $end
$upscope $end
$upscope $end
$scope task display $end
$upscope $end
$upscope $end
$enddefinitions $end
$comment Show the parameter values. $end
$dumpall
b1 <
b1100100 ;
b1101110 :
b1100101 9
b1101111 8
b0 7
$end
#0
$dumpvars
b110010 C
xB
xA
x@
x?
x>
x=
b11110 6
b10100 5
b0 4
b0 3
b0 2
b0 1
b0 0
b0 /
b0 .
b110010 -
b11110 ,
b10100 +
b0 *
b0 )
b0 (
b11110 '
b10100 &
b0 %
b0 $
b0 #
x"
b110010 !
$end
#20
0"
0?
1A
1>
0@
1B
0=
b1 .
b1 2
b1 3
b110010 !
b110010 -
b110010 C
b100000 %
b100000 *
b100000 1
b11111111111111111111111111100010 '
b11111111111111111111111111100010 ,
b11111111111111111111111111100010 6
#40
b10 .
b10 2
b10 3
1"
1?
0A
b10100 !
b10100 -
b10100 C
b0 %
b0 *
b0 1
b1 $
b1 )
b1 0
b1 4
b10 '
b10 ,
b10 6
b101 &
b101 +
b101 5
#60
b11 .
b11 2
b11 3
0"
b110 !
b110 -
b110 C
b100 $
b100 )
b100 0
b100 4
b101 '
b101 ,
b101 6
b11 &
b11 +
b11 5
#80
b100 .
b100 2
b100 3
b101 !
b101 -
b101 C
b101 $
b101 )
b101 0
b101 4
b10 '
b10 ,
b10 6
b10100 &
b10100 +
b10100 5
#100
b101 .
b101 2
b101 3
b11111111111111111111111111111011 !
b11111111111111111111111111111011 -
b11111111111111111111111111111011 C
b100000 %
b100000 *
b100000 1
b11111111111111111111111111101100 &
b11111111111111111111111111101100 +
b11111111111111111111111111101100 5
#120
b110 .
b110 2
b110 3
b1101 !
b1101 -
b1101 C
b0 %
b0 *
b0 1
b110 $
b110 )
b110 0
b110 4
b101 '
b101 ,
b101 6
b1000 &
b1000 +
b1000 5
#140
b0 !
b0 -
b0 C
b111 .
b111 2
b111 3
b111 $
b111 )
b111 0
b111 4
#160
b0 .
b0 2
b0 3
b110010 !
b110010 -
b110010 C
b1 #
b1 (
b1 /
b0 $
b0 )
b0 0
b0 4
b11110 '
b11110 ,
b11110 6
b10100 &
b10100 +
b10100 5
#180
1"
0B
1=
b1 .
b1 2
b1 3
b0 !
b0 -
b0 C
b10 #
b10 (
b10 /
b10100 '
b10100 ,
b10100 6
#200
0"
1B
0=
b1010 !
b1010 -
b1010 C
b11110 &
b11110 +
b11110 5
#220
b1000 .
b1000 2
b1000 3
b101000000000000 !
b101000000000000 -
b101000000000000 C
b11 #
b11 (
b11 /
b100 $
b100 )
b100 0
b100 4
b101 '
b101 ,
b101 6
