ImmGen.v
module ImmGen (
	input [31:0] Instruction_i,
       	output reg [31:0] Immediate_o	
);


parameter R_type	 = 5'b01100,
	  I_type1	 = 5'b00000,
	  I_type2	 = 5'b00100,
	  I_type3	 = 5'b11001,
	  S_type	 = 5'b01000,
	  B_type	 = 5'b11000,
	  U_type	 = 5'b01101,
	  J_type	 = 5'b11011;

//wire opcode [4:0];

//assign opode = Instruction_i[6:2];

always @(*) begin
	case (Instruction_i[6:2])
		R_type : Immediate_o = 32'hxxxxxxxx;

		I_type1 : Immediate_o = { {20{Instruction_i[31]}}, Instruction_i[31:20] };
		I_type2 : Immediate_o = { {20{Instruction_i[31]}}, Instruction_i[31:20] };
		I_type3 : Immediate_o = { {20{Instruction_i[31]}}, Instruction_i[31:20] };

		S_type : Immediate_o = { {20{Instruction_i[31]}}, Instruction_i[31:25], Instruction_i[11:7] };
		B_type : Immediate_o = { {19{Instruction_i[31]}}, Instruction_i[7], Instruction_i[30:25], Instruction_i[11:8], 1'b0 };
		U_type : Immediate_o = { Instruction_i[31:12], 12'b000000000000 };
		J_type : Immediate_o = { {11{Instruction_i[31]}}, Instruction_i[31], Instruction_i[19:12], Instruction_i[20], Instruction_i[30:21], 1'b0 };	
		default: Immediate_o = 32'h00000000;
	endcase

end

endmodule

ImmGen_tb.v
`timescale 1ns/1ns
`include "ImmGen.v"

module ImmGen_tb;

	reg [31:0] Instruction;
	wire [31:0] Immediate;

	ImmGen dut (
		.Instruction_i (Instruction),
		.Immediate_o (Immediate)
	);

	initial begin 

		$dumpfile ("ImmGen_tb.vcd");
		$dumpvars (0, ImmGen_tb);

		//R-type
		Instruction =32'b00000000001000001000000000110011 ; // add x0, x1, x2
		#20;
		$display("Immediate = %b or %d, expected Immediate: don't care ", Immediate, Immediate);

		//I-type 2
		Instruction =32'b00000001000100001000000000010011 ; // addi x0, x1, 17
	      	#10;
		$display("Immediate = %b or %d, expected Immediate: 17 ", Immediate, Immediate);		

		Instruction =32'b11111110111100001000000000010011 ; // addi x0, x1,-17
	      	#20;
		$display("Immediate = %b or %d, expected Immediate: -17 ", Immediate, Immediate);

		// I-type 1
		Instruction =32'b00000001100100001010000000000011 ; // lw x0, 25(x1) 
	      	#10;
		$display("Immediate = %b or %d, expected Immediate: 25 ", Immediate, Immediate);

		Instruction =32'b11111110011100001010000000000011 ; // lw x0, -25(x1) 
	      	#20;
		$display("Immediate = %b or %d, expected Immediate: -25 ", Immediate, Immediate);


		//I-type3
		Instruction =32'b00001111010100000000000011100111 ; // jalr x1, 245(x0) 
	      	#20;
		$display("Immediate = %b or %d, expected Immediate: 245  ", Immediate, Immediate);

		Instruction =32'b11110000101100000000000011100111 ; // jalr x1, -245(x0) 
	      	#10;
		$display("Immediate = %b or %d, expected Immediate: -245 ", Immediate, Immediate);

		//S-type
		Instruction =32'b01111110001011111010111110100011 ; // sw x2, 2047(x31) 
	      	#20;
		$display("Immediate = %b or %d, expected Immediate: 2047 ", Immediate, Immediate);

		Instruction =32'b10000000001011111010000010100011 ; // sw x2, -2047(x31) 
	      	#20;
		$display("Immediate = %b or %d, expected Immediate: -2047: ", Immediate, Immediate);

		//SB-type
		Instruction =32'b00000000000100000000100101100011 ; // beq x0, x1, 18 
	      	#20;
		$display("Immediate = %b or %d, expected Immediate: 18  ", Immediate, Immediate);

		Instruction =32'b11111110000100000000011111100011 ; // beq x0, x1, -18 
	      	#20;
		$display("Immediate = %b or %d, expected Immediate: -18 ", Immediate, Immediate);

		//U-type
		Instruction =32'b00000000000000110111000010110111 ; // lui x1, 55 
	      	#20;
		$display("Immediate = %b or %d, expected Immediate: 225280  ", Immediate, Immediate);

		Instruction =32'b11111111111111001001000010110111 ; // lui x1, -55 
	      	#20;
		$display("Immediate = %b or %d, expected Immediate: -225280 ", Immediate, Immediate);


		//UJ-type
		Instruction =32'b00000001010000000000000001101111 ; // jal x0, 20 
	      	#20;
		$display("Immediate = %b or %d, expected Immediate: 20 ", Immediate, Immediate);

		Instruction =32'b11111110110111111111000001101111 ; // jal x0, -20 
	      	#10;
		$display("Immediate = %b or %d, expected Immediate: -20 ", Immediate, Immediate);



	end	


endmodule

ImmGen_tb.vcd
$date
	Sat Mar 16 16:31:34 2024
$end
$version
	Icarus Verilog
$end
$timescale
	1ns
$end
$scope module ImmGen_tb $end
$var wire 32 ! Immediate [31:0] $end
$var reg 32 " Instruction [31:0] $end
$scope module dut $end
$var wire 32 # Instruction_i [31:0] $end
$var parameter 5 $ B_type $end
$var parameter 5 % I_type1 $end
$var parameter 5 & I_type2 $end
$var parameter 5 ' I_type3 $end
$var parameter 5 ( J_type $end
$var parameter 5 ) R_type $end
$var parameter 5 * S_type $end
$var parameter 5 + U_type $end
$var reg 32 , Immediate_o [31:0] $end
$upscope $end
$upscope $end
$enddefinitions $end
$comment Show the parameter values. $end
$dumpall
b1101 +
b1000 *
b1100 )
b11011 (
b11001 '
b100 &
b0 %
b11000 $
$end
#0
$dumpvars
bx ,
b1000001000000000110011 #
b1000001000000000110011 "
bx !
$end
#20
b10001 !
b10001 ,
b1000100001000000000010011 "
b1000100001000000000010011 #
#30
b11111111111111111111111111101111 !
b11111111111111111111111111101111 ,
b11111110111100001000000000010011 "
b11111110111100001000000000010011 #
#50
b11001 !
b11001 ,
b1100100001010000000000011 "
b1100100001010000000000011 #
#60
b11111111111111111111111111100111 !
b11111111111111111111111111100111 ,
b11111110011100001010000000000011 "
b11111110011100001010000000000011 #
#80
b11110101 !
b11110101 ,
b1111010100000000000011100111 "
b1111010100000000000011100111 #
#100
b11111111111111111111111100001011 !
b11111111111111111111111100001011 ,
b11110000101100000000000011100111 "
b11110000101100000000000011100111 #
#110
b11111111111 !
b11111111111 ,
b1111110001011111010111110100011 "
b1111110001011111010111110100011 #
#130
b11111111111111111111100000000001 !
b11111111111111111111100000000001 ,
b10000000001011111010000010100011 "
b10000000001011111010000010100011 #
#150
b10010 !
b10010 ,
b100000000100101100011 "
b100000000100101100011 #
#170
b1111111111111111111111111101110 !
b1111111111111111111111111101110 ,
b11111110000100000000011111100011 "
b11111110000100000000011111100011 #
#190
b110111000000000000 !
b110111000000000000 ,
b110111000010110111 "
b110111000010110111 #
#210
b11111111111111001001000000000000 !
b11111111111111001001000000000000 ,
b11111111111111001001000010110111 "
b11111111111111001001000010110111 #
#230
b10100 !
b10100 ,
b1010000000000000001101111 "
b1010000000000000001101111 #
#250
b11111111111111111111111111101100 !
b11111111111111111111111111101100 ,
b11111110110111111111000001101111 "
b11111110110111111111000001101111 #
